{
  "lastUpdated": "2026-02-17",
  "sources": ["Private Property"],
  "listings": [
    {
      "id": "T5180599",
      "title": "1 Bed - 42nd On North",
      "neighborhood": "table_view",
      "zone": "west_coast",
      "price": 995000,
      "size": 33,
      "bedrooms": 1,
      "bathrooms": 1,
      "parking": 1,
      "url": "https://www.privateproperty.co.za/for-sale/western-cape/cape-town/tableview-and-blouberg/table-view/3-42nd-on-north/42-north-road/T5180599"
    },
    {
      "id": "T5368390",
      "title": "2 Bed - Rivergate Milnerton",
      "neighborhood": "milnerton",
      "zone": "west_coast",
      "price": 975000,
      "size": 48,
      "bedrooms": 2,
      "bathrooms": 1,
      "parking": 1,
      "url": "https://www.privateproperty.co.za/for-sale/western-cape/cape-town/milnerton/rivergate/T5368390"
    },
    {
      "id": "T5177937",
      "title": "1 Bed - Residence On North",
      "neighborhood": "table_view",
      "zone": "west_coast",
      "price": 1050000,
      "size": 32,
      "bedrooms": 1,
      "bathrooms": 1,
      "parking": 1,
      "status": "Sold",
      "url": "https://www.privateproperty.co.za/for-sale/western-cape/cape-town/tableview-and-blouberg/table-view/4-residence-on-north/42-north-road/T5177937"
    },
    {
      "id": "T5355525",
      "title": "2 Bed - Seaboard Heights",
      "neighborhood": "table_view",
      "zone": "west_coast",
      "price": 1150000,
      "size": 54,
      "bedrooms": 2,
      "bathrooms": 1,
      "parking": 1,
      "url": "https://www.privateproperty.co.za/for-sale/western-cape/cape-town/tableview-and-blouberg/table-view/16-seaboard-heights/5-gill-road/T5355525"
    },
    {
      "id": "T5191146",
      "title": "1 Bed - Milnerton Central",
      "neighborhood": "milnerton",
      "zone": "west_coast",
      "price": 1180000,
      "size": 42,
      "bedrooms": 1,
      "bathrooms": 1,
      "parking": 1,
      "url": "https://www.privateproperty.co.za/for-sale/western-cape/cape-town/milnerton/milnerton-central/T5191146"
    },
    {
      "id": "T5187180",
      "title": "1 Bed - Bali Mews",
      "neighborhood": "table_view",
      "zone": "west_coast",
      "price": 1249999,
      "size": 48,
      "bedrooms": 1,
      "bathrooms": 1,
      "parking": 1,
      "url": "https://www.privateproperty.co.za/for-sale/western-cape/cape-town/tableview-and-blouberg/table-view/9-ss-bali-mews/9-north-road/T5187180"
    },
    {
      "id": "T5345726",
      "title": "1 Bed - Bali Mews North",
      "neighborhood": "table_view",
      "zone": "west_coast",
      "price": 1250000,
      "size": 48,
      "bedrooms": 1,
      "bathrooms": 1,
      "parking": 1,
      "url": "https://www.privateproperty.co.za/for-sale/western-cape/cape-town/tableview-and-blouberg/table-view/9-ss-bali-mews/37-north-road/T5345726"
    },
    {
      "id": "T5358595",
      "title": "1 Bed Apartment Table View",
      "neighborhood": "table_view",
      "zone": "west_coast",
      "price": 1299000,
      "size": 41,
      "bedrooms": 1,
      "bathrooms": 1,
      "parking": 1,
      "url": "https://www.privateproperty.co.za/for-sale/western-cape/cape-town/tableview-and-blouberg/table-view/T5358595"
    },
    {
      "id": "T5382025",
      "title": "1 Bed - Seaboard Mews",
      "neighborhood": "table_view",
      "zone": "west_coast",
      "price": 1350000,
      "size": 41,
      "bedrooms": 1,
      "bathrooms": 1,
      "parking": 1,
      "url": "https://www.privateproperty.co.za/for-sale/western-cape/cape-town/tableview-and-blouberg/table-view/22-seaboard-mews/137-blaauwberg-road/T5382025"
    },
    {
      "id": "T5366601",
      "title": "1 Bed - Richwood Milnerton",
      "neighborhood": "milnerton",
      "zone": "west_coast",
      "price": 1350000,
      "size": 60,
      "bedrooms": 1,
      "bathrooms": 1,
      "parking": 1,
      "url": "https://www.privateproperty.co.za/for-sale/western-cape/cape-town/milnerton/richwood/T5366601"
    },
    {
      "id": "T5384945",
      "title": "1 Bed - 42 On South (New)",
      "neighborhood": "table_view",
      "zone": "west_coast",
      "price": 1375000,
      "size": 43,
      "bedrooms": 1,
      "bathrooms": 1,
      "parking": 1,
      "status": "New",
      "url": "https://www.privateproperty.co.za/for-sale/western-cape/cape-town/tableview-and-blouberg/table-view/7-42-on-south/42-south-road/T5384945"
    },
    {
      "id": "T5325869",
      "title": "1 Bed - 42 On South",
      "neighborhood": "table_view",
      "zone": "west_coast",
      "price": 1385000,
      "size": 43,
      "bedrooms": 1,
      "bathrooms": 1,
      "parking": 1,
      "url": "https://www.privateproperty.co.za/for-sale/western-cape/cape-town/tableview-and-blouberg/table-view/13-42-on-south/42-south-road/T5325869"
    },
    {
      "id": "T5360295",
      "title": "1 Bed - 42 On South",
      "neighborhood": "table_view",
      "zone": "west_coast",
      "price": 1410000,
      "size": 43,
      "bedrooms": 1,
      "bathrooms": 1,
      "parking": 1,
      "url": "https://www.privateproperty.co.za/for-sale/western-cape/cape-town/tableview-and-blouberg/table-view/26-42-on-south/42-south-road/T5360295"
    },
    {
      "id": "T5382026",
      "title": "1 Bed - Seaboard Mews",
      "neighborhood": "table_view",
      "zone": "west_coast",
      "price": 1450000,
      "size": 43,
      "bedrooms": 1,
      "bathrooms": 1,
      "parking": 1,
      "url": "https://www.privateproperty.co.za/for-sale/western-cape/cape-town/tableview-and-blouberg/table-view/8-seaboard-mews/137-blaauwberg-road/T5382026"
    },
    {
      "id": "T5382029",
      "title": "1 Bed - Seaboard Mews",
      "neighborhood": "table_view",
      "zone": "west_coast",
      "price": 1495000,
      "size": 53,
      "bedrooms": 1,
      "bathrooms": 1,
      "parking": 1,
      "url": "https://www.privateproperty.co.za/for-sale/western-cape/cape-town/tableview-and-blouberg/table-view/9-seaboard-mews/137-blaauwberg-road/T5382029"
    },
    {
      "id": "T5236288",
      "title": "1 Bed - Cornerstone On Arum",
      "neighborhood": "table_view",
      "zone": "west_coast",
      "price": 1500000,
      "size": 45,
      "bedrooms": 1,
      "bathrooms": 1,
      "parking": 1,
      "url": "https://www.privateproperty.co.za/for-sale/western-cape/cape-town/tableview-and-blouberg/table-view/106-cornerstone-on-arum/154-arum-road/T5236288"
    },
    {
      "id": "T4451880",
      "title": "2 Bed - Burgundy Estate",
      "neighborhood": "milnerton",
      "zone": "west_coast",
      "price": 1696000,
      "size": 65,
      "bedrooms": 2,
      "bathrooms": 2,
      "parking": 1,
      "url": "https://www.privateproperty.co.za/for-sale/western-cape/cape-town/milnerton/burgundy-estate/T4451880"
    },
    {
      "id": "T5346255",
      "title": "1 Bed - 108 Nautica",
      "neighborhood": "table_view",
      "zone": "west_coast",
      "price": 1790000,
      "size": 31,
      "bedrooms": 1,
      "bathrooms": 1,
      "parking": 1,
      "status": "Under Offer",
      "url": "https://www.privateproperty.co.za/for-sale/western-cape/cape-town/tableview-and-blouberg/table-view/108-nautica/16-clam-road-table-view/T5346255"
    },
    {
      "id": "T5392175",
      "title": "2 Bed - Burgundy Estate",
      "neighborhood": "milnerton",
      "zone": "west_coast",
      "price": 1846000,
      "size": 70,
      "bedrooms": 2,
      "bathrooms": 1,
      "parking": 1,
      "url": "https://www.privateproperty.co.za/for-sale/western-cape/cape-town/milnerton/burgundy-estate/T5392175"
    },
    {
      "id": "T5322982",
      "title": "1 Bed - Big Bay",
      "neighborhood": "big_bay",
      "zone": "west_coast",
      "price": 2095000,
      "size": 53,
      "bedrooms": 1,
      "bathrooms": 1,
      "parking": 1,
      "status": "Under Offer",
      "url": "https://www.privateproperty.co.za/for-sale/western-cape/cape-town/tableview-and-blouberg/big-bay/T5322982"
    },
    {
      "id": "T5361365",
      "title": "2 Bed - Big Bay Anignon",
      "neighborhood": "big_bay",
      "zone": "west_coast",
      "price": 2795000,
      "size": 70,
      "bedrooms": 2,
      "bathrooms": 1,
      "parking": 1,
      "status": "Under Offer",
      "url": "https://www.privateproperty.co.za/for-sale/western-cape/cape-town/tableview-and-blouberg/big-bay/190-anignon/76-sumatra-avenue/T5361365"
    },
    {
      "id": "T5213377",
      "title": "1 Bed - Eden On The Bay",
      "neighborhood": "big_bay",
      "zone": "west_coast",
      "price": 2995000,
      "size": 53,
      "bedrooms": 1,
      "bathrooms": 1,
      "parking": 1,
      "url": "https://www.privateproperty.co.za/for-sale/western-cape/cape-town/tableview-and-blouberg/big-bay/181-ss-eden-on-the-bay/5-beach-estate-boulevard/T5213377"
    },
    {
      "id": "T5363815",
      "title": "Studio - Montclaire Sea Point",
      "neighborhood": "sea_point",
      "zone": "atlantic_seaboard",
      "price": 2495000,
      "size": 33,
      "bedrooms": 0,
      "bathrooms": 1,
      "parking": 0,
      "favorite": true,
      "favoriteReason": "Vue Signal Hill, proche promenade, Airbnb autorise",
      "url": "https://www.privateproperty.co.za/for-sale/western-cape/cape-town/atlantic-seaboard/sea-point/603-montclaire/4-frere-road/T5363815"
    },
    {
      "id": "T5300131",
      "title": "Studio - Three43onb Sea Point",
      "neighborhood": "sea_point",
      "zone": "atlantic_seaboard",
      "price": 2950000,
      "size": 28,
      "bedrooms": 0,
      "bathrooms": 1,
      "parking": 0,
      "url": "https://www.privateproperty.co.za/for-sale/western-cape/cape-town/atlantic-seaboard/sea-point/217-three43onb/217-217/T5300131"
    },
    {
      "id": "T5256904",
      "title": "Studio - Harbour Terrace Green Point",
      "neighborhood": "green_point",
      "zone": "atlantic_seaboard",
      "price": 2999999,
      "size": 39,
      "bedrooms": 0,
      "bathrooms": 1,
      "parking": 0,
      "url": "https://www.privateproperty.co.za/for-sale/western-cape/cape-town/atlantic-seaboard/green-point/90-harbour-terrace/9-boundary-road/T5256904"
    },
    {
      "id": "T5383233",
      "title": "1 Bed - Green Point Central",
      "neighborhood": "green_point",
      "zone": "atlantic_seaboard",
      "price": 2695000,
      "size": 51,
      "bedrooms": 1,
      "bathrooms": 1,
      "parking": 1,
      "favorite": true,
      "favoriteReason": "Proche stade, renove, bon R/m2",
      "url": "https://www.privateproperty.co.za/for-sale/western-cape/cape-town/atlantic-seaboard/green-point/T5383233"
    },
    {
      "id": "T5385178",
      "title": "1 Bed - Green Point",
      "neighborhood": "green_point",
      "zone": "atlantic_seaboard",
      "price": 2950000,
      "size": 50,
      "bedrooms": 1,
      "bathrooms": 1,
      "parking": 1,
      "url": "https://www.privateproperty.co.za/for-sale/western-cape/cape-town/atlantic-seaboard/green-point/T5385178"
    },
    {
      "id": "T5107350",
      "title": "Studio - Three Anchor Bay",
      "neighborhood": "three_anchor_bay",
      "zone": "atlantic_seaboard",
      "price": 2495000,
      "size": 42,
      "bedrooms": 0,
      "bathrooms": 1,
      "parking": 1,
      "status": "Under Offer",
      "url": "https://www.privateproperty.co.za/for-sale/western-cape/cape-town/atlantic-seaboard/three-anchor-bay/T5107350"
    },
    {
      "id": "T4397265",
      "title": "1 Bed - Quayside De Waterkant",
      "neighborhood": "de_waterkant",
      "zone": "city_bowl",
      "price": 2199000,
      "size": 67,
      "bedrooms": 1,
      "bathrooms": 1,
      "parking": 1,
      "favorite": true,
      "favoriteReason": "De Waterkant trendy, bon m2, proche V&A",
      "url": "https://www.privateproperty.co.za/for-sale/western-cape/cape-town/cape-town-city-bowl/de-waterkant/4-quayside/34-prestwich-street/T4397265"
    },
    {
      "id": "T5340105",
      "title": "Studio - The Rose De Waterkant",
      "neighborhood": "de_waterkant",
      "zone": "city_bowl",
      "price": 2500000,
      "size": 28,
      "bedrooms": 0,
      "bathrooms": 1,
      "parking": 0,
      "status": "Under Offer",
      "url": "https://www.privateproperty.co.za/for-sale/western-cape/cape-town/cape-town-city-bowl/de-waterkant/607-the-rose/117-strand-street/T5340105"
    },
    {
      "id": "T5076482",
      "title": "1 Bed - De Waterkant",
      "neighborhood": "de_waterkant",
      "zone": "city_bowl",
      "price": 2895000,
      "size": 45,
      "bedrooms": 1,
      "bathrooms": 1,
      "parking": 1,
      "status": "Under Offer",
      "url": "https://www.privateproperty.co.za/for-sale/western-cape/cape-town/cape-town-city-bowl/de-waterkant/T5076482"
    },
    {
      "id": "T5142064",
      "title": "2 Bed - Bo-Kaap",
      "neighborhood": "bo_kaap",
      "zone": "city_bowl",
      "price": 1750000,
      "size": 50,
      "bedrooms": 2,
      "bathrooms": 1,
      "parking": 0,
      "favorite": true,
      "favoriteReason": "Bo-Kaap culturel, bon prix/m2, touristes",
      "url": "https://www.privateproperty.co.za/for-sale/western-cape/cape-town/cape-town-city-bowl/bo-kaap/T5142064"
    },
    {
      "id": "T5176914",
      "title": "2 Bed - Bo-Kaap",
      "neighborhood": "bo_kaap",
      "zone": "city_bowl",
      "price": 1800000,
      "size": 48,
      "bedrooms": 2,
      "bathrooms": 1,
      "parking": 0,
      "status": "Under Offer",
      "url": "https://www.privateproperty.co.za/for-sale/western-cape/cape-town/cape-town-city-bowl/bo-kaap/T5176914"
    },
    {
      "id": "T4851488",
      "title": "Studio Micro - City Centre",
      "neighborhood": "cape_town_city_centre",
      "zone": "city_bowl",
      "price": 1100000,
      "size": 24,
      "bedrooms": 0,
      "bathrooms": 1,
      "parking": 0,
      "url": "https://www.privateproperty.co.za/for-sale/western-cape/cape-town/cape-town-city-bowl/cape-town-city-centre/T4851488"
    },
    {
      "id": "T5354035",
      "title": "Studio - City Centre",
      "neighborhood": "cape_town_city_centre",
      "zone": "city_bowl",
      "price": 1450000,
      "size": 29,
      "bedrooms": 1,
      "bathrooms": 1,
      "parking": 0,
      "url": "https://www.privateproperty.co.za/for-sale/western-cape/cape-town/cape-town-city-bowl/cape-town-city-centre/T5354035"
    },
    {
      "id": "T5227045",
      "title": "Studio - Tenonv Vredenburg",
      "neighborhood": "cape_town_city_centre",
      "zone": "city_bowl",
      "price": 1550000,
      "size": 20,
      "bedrooms": 0,
      "bathrooms": 1,
      "parking": 0,
      "url": "https://www.privateproperty.co.za/for-sale/western-cape/cape-town/cape-town-city-bowl/cape-town-city-centre/104-tenonv/104-vredenburg-lane/T5227045"
    },
    {
      "id": "T5282012",
      "title": "Studio - Tuynhuys Keerom",
      "neighborhood": "cape_town_city_centre",
      "zone": "city_bowl",
      "price": 1650000,
      "size": 25,
      "bedrooms": 0,
      "bathrooms": 1,
      "parking": 0,
      "url": "https://www.privateproperty.co.za/for-sale/western-cape/cape-town/cape-town-city-bowl/cape-town-city-centre/54-keerom-street/405-tuynhuys-c/T5282012"
    },
    {
      "id": "T5289429",
      "title": "Studio - Loop Street",
      "neighborhood": "cape_town_city_centre",
      "zone": "city_bowl",
      "price": 1750000,
      "size": 33,
      "bedrooms": 0,
      "bathrooms": 1,
      "parking": 0,
      "url": "https://www.privateproperty.co.za/for-sale/western-cape/cape-town/cape-town-city-bowl/cape-town-city-centre/0-cape-town-city-centre/112-loop-st/T5289429"
    },
    {
      "id": "T5269210",
      "title": "Studio - Tuynhuys Building",
      "neighborhood": "cape_town_city_centre",
      "zone": "city_bowl",
      "price": 1750000,
      "size": 38,
      "bedrooms": 0,
      "bathrooms": 1,
      "parking": 0,
      "url": "https://www.privateproperty.co.za/for-sale/western-cape/cape-town/cape-town-city-bowl/cape-town-city-centre/203-tuynhuys-building/54-keerom-street/T5269210"
    },
    {
      "id": "T5322598",
      "title": "1 Bed - Four Seasons Buitenkant",
      "neighborhood": "cape_town_city_centre",
      "zone": "city_bowl",
      "price": 1850000,
      "size": 54,
      "bedrooms": 1,
      "bathrooms": 1,
      "parking": 1,
      "url": "https://www.privateproperty.co.za/for-sale/western-cape/cape-town/cape-town-city-bowl/cape-town-city-centre/808-four-seasons/43-buitenkant-st/T5322598"
    },
    {
      "id": "T5345151",
      "title": "1 Bed - St Georges Mall",
      "neighborhood": "cape_town_city_centre",
      "zone": "city_bowl",
      "price": 1995000,
      "size": 65,
      "bedrooms": 1,
      "bathrooms": 1,
      "parking": 0,
      "url": "https://www.privateproperty.co.za/for-sale/western-cape/cape-town/cape-town-city-bowl/cape-town-city-centre/34-st-georges/34-st-georges-mall/T5345151"
    },
    {
      "id": "T5322277",
      "title": "1 Bed - Colosseum St Georges",
      "neighborhood": "cape_town_city_centre",
      "zone": "city_bowl",
      "price": 1995000,
      "size": 67,
      "bedrooms": 1,
      "bathrooms": 1,
      "parking": 0,
      "url": "https://www.privateproperty.co.za/for-sale/western-cape/cape-town/cape-town-city-bowl/cape-town-city-centre/colosseum/3-st-georges-mall/T5322277"
    },
    {
      "id": "T5390009",
      "title": "1 Bed - Greenmarket Place",
      "neighborhood": "cape_town_city_centre",
      "zone": "city_bowl",
      "price": 2200000,
      "size": 59,
      "bedrooms": 1,
      "bathrooms": 1,
      "parking": 0,
      "url": "https://www.privateproperty.co.za/for-sale/western-cape/cape-town/cape-town-city-bowl/cape-town-city-centre/801-greenmarket-place/54a-shortmarket-street/T5390009"
    },
    {
      "id": "T5336715",
      "title": "1 Bed - Wembley Square Gardens",
      "neighborhood": "gardens",
      "zone": "city_bowl_upper",
      "price": 2275000,
      "size": 46,
      "bedrooms": 1,
      "bathrooms": 1,
      "parking": 0,
      "url": "https://www.privateproperty.co.za/for-sale/western-cape/cape-town/cape-town-city-bowl/gardens/wembley-square/40-solan-road/T5336715"
    },
    {
      "id": "T5021953",
      "title": "1 Bed - Black Brick Gardens",
      "neighborhood": "gardens",
      "zone": "city_bowl_upper",
      "price": 2595000,
      "size": 44,
      "bedrooms": 1,
      "bathrooms": 1,
      "parking": 0,
      "url": "https://www.privateproperty.co.za/for-sale/western-cape/cape-town/cape-town-city-bowl/gardens/112-black-brick/2-roodehek/T5021953"
    },
    {
      "id": "T5021714",
      "title": "1 Bed - Black Brick 404",
      "neighborhood": "gardens",
      "zone": "city_bowl_upper",
      "price": 2695000,
      "size": 36,
      "bedrooms": 1,
      "bathrooms": 1,
      "parking": 0,
      "url": "https://www.privateproperty.co.za/for-sale/western-cape/cape-town/cape-town-city-bowl/gardens/404-black-brick/2-roodehek/T5021714"
    },
    {
      "id": "T5021715",
      "title": "1 Bed - Black Brick 412",
      "neighborhood": "gardens",
      "zone": "city_bowl_upper",
      "price": 2745000,
      "size": 44,
      "bedrooms": 1,
      "bathrooms": 1,
      "parking": 0,
      "url": "https://www.privateproperty.co.za/for-sale/western-cape/cape-town/cape-town-city-bowl/gardens/412-black-brick/2-roodehek/T5021715"
    },
    {
      "id": "T5024504",
      "title": "1 Bed - Disa Park Vredehoek",
      "neighborhood": "vredehoek",
      "zone": "city_bowl_upper",
      "price": 1590000,
      "size": 49,
      "bedrooms": 1,
      "bathrooms": 1,
      "parking": 0,
      "url": "https://www.privateproperty.co.za/for-sale/western-cape/cape-town/cape-town-city-bowl/vredehoek/T5024504"
    },
    {
      "id": "T5357853",
      "title": "1 Bed - Shavron Court Vredehoek",
      "neighborhood": "vredehoek",
      "zone": "city_bowl_upper",
      "price": 1995000,
      "size": 38,
      "bedrooms": 1,
      "bathrooms": 1,
      "parking": 0,
      "url": "https://www.privateproperty.co.za/for-sale/western-cape/cape-town/cape-town-city-bowl/vredehoek/0-shavron-court/9-chelmsford-rd/T5357853"
    },
    {
      "id": "T5314472",
      "title": "1 Bed - Chudliegh Tamboerskloof",
      "neighborhood": "tamboerskloof",
      "zone": "city_bowl_upper",
      "price": 2750000,
      "size": 55,
      "bedrooms": 1,
      "bathrooms": 1,
      "parking": 0,
      "status": "Under Offer",
      "url": "https://www.privateproperty.co.za/for-sale/western-cape/cape-town/cape-town-city-bowl/tamboerskloof/9-chudliegh-court/20-carstens-st-c/T5314472"
    },
    {
      "id": "T5157125",
      "title": "Studio - 1 On Albert Woodstock",
      "neighborhood": "woodstock",
      "zone": "eastern",
      "price": 1143000,
      "size": 27,
      "bedrooms": 0,
      "bathrooms": 1,
      "parking": 0,
      "status": "Under Offer",
      "favorite": true,
      "favoriteReason": "Woodstock gentrification, piscine, gym, Airbnb-friendly",
      "url": "https://www.privateproperty.co.za/for-sale/western-cape/cape-town/cape-town-city-bowl/woodstock/518-1-on-albert/1a-albert-road/T5157125"
    },
    {
      "id": "T5180226",
      "title": "Studio - Harbour View Woodstock",
      "neighborhood": "woodstock",
      "zone": "eastern",
      "price": 1150000,
      "size": 37,
      "bedrooms": 0,
      "bathrooms": 1,
      "parking": 0,
      "url": "https://www.privateproperty.co.za/for-sale/western-cape/cape-town/cape-town-city-bowl/woodstock/a612-harbour-view/4-bromwell-street/T5180226"
    },
    {
      "id": "T5381701",
      "title": "Studio - One on Albert 702",
      "neighborhood": "woodstock",
      "zone": "eastern",
      "price": 1250000,
      "size": 24,
      "bedrooms": 0,
      "bathrooms": 1,
      "parking": 0,
      "url": "https://www.privateproperty.co.za/for-sale/western-cape/cape-town/cape-town-city-bowl/woodstock/702-one-on-albert/1a-albert-street/T5381701"
    },
    {
      "id": "T5091525",
      "title": "Studio - Urban Artisan Woodstock",
      "neighborhood": "woodstock",
      "zone": "eastern",
      "price": 1280000,
      "size": 41,
      "bedrooms": 0,
      "bathrooms": 1,
      "parking": 0,
      "url": "https://www.privateproperty.co.za/for-sale/western-cape/cape-town/cape-town-city-bowl/woodstock/605-urban-artisan/22-salt-river-road/T5091525"
    },
    {
      "id": "T5030374",
      "title": "1 Bed - WEX 1 Woodstock",
      "neighborhood": "woodstock",
      "zone": "eastern",
      "price": 1695000,
      "size": 42,
      "bedrooms": 1,
      "bathrooms": 1,
      "parking": 0,
      "url": "https://www.privateproperty.co.za/for-sale/western-cape/cape-town/cape-town-city-bowl/woodstock/T5030374"
    },
    {
      "id": "T5274224",
      "title": "2 Bed - Woodstock",
      "neighborhood": "woodstock",
      "zone": "eastern",
      "price": 1995000,
      "size": 77,
      "bedrooms": 2,
      "bathrooms": 1,
      "parking": 0,
      "url": "https://www.privateproperty.co.za/for-sale/western-cape/cape-town/cape-town-city-bowl/woodstock/T5274224"
    },
    {
      "id": "T5178228",
      "title": "2 Bed - WEX 1 430 Woodstock",
      "neighborhood": "woodstock",
      "zone": "eastern",
      "price": 2195000,
      "size": 70,
      "bedrooms": 2,
      "bathrooms": 1,
      "parking": 0,
      "url": "https://www.privateproperty.co.za/for-sale/western-cape/cape-town/cape-town-city-bowl/woodstock/430-wex-1/85-albert-road/T5178228"
    },
    {
      "id": "T5172765",
      "title": "2 Bed - WEX 1 421 Woodstock",
      "neighborhood": "woodstock",
      "zone": "eastern",
      "price": 2695000,
      "size": 84,
      "bedrooms": 2,
      "bathrooms": 1,
      "parking": 1,
      "url": "https://www.privateproperty.co.za/for-sale/western-cape/cape-town/cape-town-city-bowl/woodstock/421-wex-1/85-albert-road/T5172765"
    },
    {
      "id": "T5231497",
      "title": "1 Bed - Shonsay Observatory",
      "neighborhood": "observatory",
      "zone": "eastern",
      "price": 1120000,
      "size": 42,
      "bedrooms": 1,
      "bathrooms": 1,
      "parking": 0,
      "favorite": true,
      "favoriteReason": "Obs etudiant, bon prix, proche cafes",
      "url": "https://www.privateproperty.co.za/for-sale/western-cape/cape-town/cape-town-city-bowl/observatory/13-shonsay/24-lytton-st/T5231497"
    },
    {
      "id": "T5252152",
      "title": "Studio - Obs Court",
      "neighborhood": "observatory",
      "zone": "eastern",
      "price": 1350000,
      "size": 37,
      "bedrooms": 0,
      "bathrooms": 1,
      "parking": 0,
      "url": "https://www.privateproperty.co.za/for-sale/western-cape/cape-town/cape-town-city-bowl/observatory/0-obs-court/5-howe-street/T5252152"
    },
    {
      "id": "T5389806",
      "title": "1 Bed - Obs Court 131",
      "neighborhood": "observatory",
      "zone": "eastern",
      "price": 1475000,
      "size": 37,
      "bedrooms": 1,
      "bathrooms": 1,
      "parking": 1,
      "favorite": true,
      "favoriteReason": "Meuble, vue montagne, R12-13k loyer potentiel",
      "url": "https://www.privateproperty.co.za/for-sale/western-cape/cape-town/cape-town-city-bowl/observatory/131-obs-court/3a-howe-street/T5389806"
    },
    {
      "id": "T4794183",
      "title": "1 Bed - Obs Court 839",
      "neighborhood": "observatory",
      "zone": "eastern",
      "price": 1495000,
      "size": 49,
      "bedrooms": 1,
      "bathrooms": 1,
      "parking": 1,
      "url": "https://www.privateproperty.co.za/for-sale/western-cape/cape-town/cape-town-city-bowl/observatory/839-obs-court/3a-howe-street/T4794183"
    },
    {
      "id": "T5378025",
      "title": "2 Bed - The Factory Observatory",
      "neighborhood": "observatory",
      "zone": "eastern",
      "price": 1745000,
      "size": 79,
      "bedrooms": 2,
      "bathrooms": 2,
      "parking": 1,
      "url": "https://www.privateproperty.co.za/for-sale/western-cape/cape-town/cape-town-city-bowl/observatory/410-the-factory/1-howe-street/T5378025"
    },
    {
      "id": "T5252202",
      "title": "2 Bed - Obs Court",
      "neighborhood": "observatory",
      "zone": "eastern",
      "price": 1895000,
      "size": 65,
      "bedrooms": 2,
      "bathrooms": 2,
      "parking": 1,
      "url": "https://www.privateproperty.co.za/for-sale/western-cape/cape-town/cape-town-city-bowl/observatory/0-obs-court/3a-howe-street/T5252202"
    },
    {
      "id": "T5184138",
      "title": "2 Bed - The Paragon Observatory",
      "neighborhood": "observatory",
      "zone": "eastern",
      "price": 1950000,
      "size": 68,
      "bedrooms": 2,
      "bathrooms": 2,
      "parking": 1,
      "url": "https://www.privateproperty.co.za/for-sale/western-cape/cape-town/cape-town-city-bowl/observatory/0-the-paragon/423-main-road/T5184138"
    },
    {
      "id": "T5349680",
      "title": "2 Bed - Madison Place Observatory",
      "neighborhood": "observatory",
      "zone": "eastern",
      "price": 2800000,
      "size": 71,
      "bedrooms": 2,
      "bathrooms": 2,
      "parking": 1,
      "url": "https://www.privateproperty.co.za/for-sale/western-cape/cape-town/cape-town-city-bowl/observatory/0-madison-place/6-trill-rd/T5349680"
    },
    {
      "id": "T5358764",
      "title": "1 Bed - Durham Square Salt River",
      "neighborhood": "salt_river",
      "zone": "eastern",
      "price": 1100000,
      "size": 56,
      "bedrooms": 1,
      "bathrooms": 1,
      "parking": 0,
      "status": "Under Offer",
      "url": "https://www.privateproperty.co.za/for-sale/western-cape/cape-town/cape-town-city-bowl/salt-river/409-durham-square/267-victoria-road/T5358764"
    },
    {
      "id": "T5334551",
      "title": "2 Bed - Durham Square Salt River",
      "neighborhood": "salt_river",
      "zone": "eastern",
      "price": 1490000,
      "size": 76,
      "bedrooms": 2,
      "bathrooms": 2,
      "parking": 1,
      "status": "Under Offer",
      "url": "https://www.privateproperty.co.za/for-sale/western-cape/cape-town/cape-town-city-bowl/salt-river/T5334551"
    },
    {
      "id": "T5292755",
      "title": "1 Bed - Swift Studios Salt River",
      "neighborhood": "salt_river",
      "zone": "eastern",
      "price": 1525000,
      "size": 71,
      "bedrooms": 1,
      "bathrooms": 1,
      "parking": 1,
      "status": "Under Offer",
      "url": "https://www.privateproperty.co.za/for-sale/western-cape/cape-town/cape-town-city-bowl/salt-river/8-swift-studios/97-cecil-road/T5292755"
    },
    {
      "id": "T5381722",
      "title": "2 Bed - Upper Eastside Salt River",
      "neighborhood": "salt_river",
      "zone": "eastern",
      "price": 2300000,
      "size": 78,
      "bedrooms": 2,
      "bathrooms": 2,
      "parking": 1,
      "url": "https://www.privateproperty.co.za/for-sale/western-cape/cape-town/cape-town-city-bowl/salt-river/305-upper-eastside/31-brickfield-road/T5381722"
    },
    {
      "id": "T5212946",
      "title": "2 Bed - Upper East Side Salt River",
      "neighborhood": "salt_river",
      "zone": "eastern",
      "price": 2999500,
      "size": 89,
      "bedrooms": 2,
      "bathrooms": 2,
      "parking": 2,
      "status": "Under Offer",
      "url": "https://www.privateproperty.co.za/for-sale/western-cape/cape-town/cape-town-city-bowl/salt-river/1509-upper-east-side/31-brickfield-road/T5212946"
    },
    {
      "id": "T5296190",
      "title": "1 Bed - The Claremont",
      "neighborhood": "claremont",
      "zone": "southern_suburbs",
      "price": 1600000,
      "size": 40,
      "bedrooms": 1,
      "bathrooms": 1,
      "parking": 0,
      "url": "https://www.privateproperty.co.za/for-sale/western-cape/cape-town/southern-suburbs/claremont/the-claremont/53-main-rd/T5296190"
    },
    {
      "id": "T5215517",
      "title": "2 Bed - Prince Charles Mansions",
      "neighborhood": "claremont",
      "zone": "southern_suburbs",
      "price": 2195000,
      "size": 71,
      "bedrooms": 2,
      "bathrooms": 1,
      "parking": 1,
      "status": "Under Offer",
      "url": "https://www.privateproperty.co.za/for-sale/western-cape/cape-town/southern-suburbs/claremont/claremont-upper/1-prince-charles-mansions/255-main-rd/T5215517"
    },
    {
      "id": "T5374391",
      "title": "1 Bed - Willow Grange Claremont",
      "neighborhood": "claremont",
      "zone": "southern_suburbs",
      "price": 2450000,
      "size": 58,
      "bedrooms": 1,
      "bathrooms": 1,
      "parking": 0,
      "status": "Under Offer",
      "url": "https://www.privateproperty.co.za/for-sale/western-cape/cape-town/southern-suburbs/claremont/claremont-upper/9-willow-grange/6-church-street/T5374391"
    },
    {
      "id": "T5382382",
      "title": "2 Bed - Prince Charles 12",
      "neighborhood": "claremont",
      "zone": "southern_suburbs",
      "price": 2495000,
      "size": 70,
      "bedrooms": 2,
      "bathrooms": 1,
      "parking": 1,
      "url": "https://www.privateproperty.co.za/for-sale/western-cape/cape-town/southern-suburbs/claremont/claremont-upper/12-prince-charles-mansions/255-main-road/T5382382"
    },
    {
      "id": "T5315081",
      "title": "2 Bed - The Claremont",
      "neighborhood": "claremont",
      "zone": "southern_suburbs",
      "price": 2495000,
      "size": 81,
      "bedrooms": 2,
      "bathrooms": 2,
      "parking": 2,
      "status": "Under Offer",
      "url": "https://www.privateproperty.co.za/for-sale/western-cape/cape-town/southern-suburbs/claremont/claremont-upper/0-the-claremont/53-main-road/T5315081"
    },
    {
      "id": "T5315389",
      "title": "2 Bed - The Beaumont Claremont",
      "neighborhood": "claremont",
      "zone": "southern_suburbs",
      "price": 2595000,
      "size": 58,
      "bedrooms": 2,
      "bathrooms": 1,
      "parking": 1,
      "status": "Under Offer",
      "url": "https://www.privateproperty.co.za/for-sale/western-cape/cape-town/southern-suburbs/claremont/claremont-upper/g208-the-beaumont/13-grove-ave/T5315389"
    },
    {
      "id": "T5106599",
      "title": "2 Bed - Imam Haron Claremont",
      "neighborhood": "claremont",
      "zone": "southern_suburbs",
      "price": 2650000,
      "size": 65,
      "bedrooms": 2,
      "bathrooms": 1,
      "parking": 1,
      "url": "https://www.privateproperty.co.za/for-sale/western-cape/cape-town/southern-suburbs/claremont/144-imam-haron-road/T5106599"
    },
    {
      "id": "T4878810",
      "title": "2 Bed - Seven Miles South",
      "neighborhood": "claremont",
      "zone": "southern_suburbs",
      "price": 2795000,
      "size": 90,
      "bedrooms": 2,
      "bathrooms": 2,
      "parking": 1,
      "url": "https://www.privateproperty.co.za/for-sale/western-cape/cape-town/southern-suburbs/claremont/claremont-upper/611-seven-miles-south/611-main-road/T4878810"
    },
    {
      "id": "T5130975",
      "title": "Studio - Evergreen Rondebosch",
      "neighborhood": "rondebosch",
      "zone": "southern_suburbs",
      "price": 1395000,
      "size": 35,
      "bedrooms": 0,
      "bathrooms": 1,
      "parking": 0,
      "url": "https://www.privateproperty.co.za/for-sale/western-cape/cape-town/southern-suburbs/rondebosch/104-evergreen/7-fir-road/T5130975"
    },
    {
      "id": "T5263419",
      "title": "1 Bed - Devon View Rondebosch",
      "neighborhood": "rondebosch",
      "zone": "southern_suburbs",
      "price": 1600000,
      "size": 47,
      "bedrooms": 1,
      "bathrooms": 1,
      "parking": 1,
      "url": "https://www.privateproperty.co.za/for-sale/western-cape/cape-town/southern-suburbs/rondebosch/10-ss-devon-view/8-devonshire-hill-road/T5263419"
    },
    {
      "id": "T5028322",
      "title": "1 Bed - College Road Rondebosch",
      "neighborhood": "rondebosch",
      "zone": "southern_suburbs",
      "price": 1635000,
      "size": 42,
      "bedrooms": 1,
      "bathrooms": 1,
      "parking": 0,
      "url": "https://www.privateproperty.co.za/for-sale/western-cape/cape-town/southern-suburbs/rondebosch/6-college-rd/T5028322"
    },
    {
      "id": "T5308645",
      "title": "Studio - Rondebosch",
      "neighborhood": "rondebosch",
      "zone": "southern_suburbs",
      "price": 1850000,
      "size": 31,
      "bedrooms": 0,
      "bathrooms": 1,
      "parking": 0,
      "url": "https://www.privateproperty.co.za/for-sale/western-cape/cape-town/southern-suburbs/rondebosch/T5308645"
    },
    {
      "id": "T5297828",
      "title": "1 Bed - Harion Court Rondebosch",
      "neighborhood": "rondebosch",
      "zone": "southern_suburbs",
      "price": 1850000,
      "size": 69,
      "bedrooms": 1,
      "bathrooms": 1,
      "parking": 1,
      "url": "https://www.privateproperty.co.za/for-sale/western-cape/cape-town/southern-suburbs/rondebosch/4-harion-court/51-albion/T5297828"
    },
    {
      "id": "T5301433",
      "title": "2 Bed - Hillside Flats Rondebosch",
      "neighborhood": "rondebosch",
      "zone": "southern_suburbs",
      "price": 1995000,
      "size": 48,
      "bedrooms": 2,
      "bathrooms": 2,
      "parking": 2,
      "url": "https://www.privateproperty.co.za/for-sale/western-cape/cape-town/southern-suburbs/rondebosch/1-hillside-flats/7-church/T5301433"
    },
    {
      "id": "T5383014",
      "title": "2 Bed - Edingight Rondebosch",
      "neighborhood": "rondebosch",
      "zone": "southern_suburbs",
      "price": 2895000,
      "size": 78,
      "bedrooms": 2,
      "bathrooms": 2,
      "parking": 1,
      "url": "https://www.privateproperty.co.za/for-sale/western-cape/cape-town/southern-suburbs/rondebosch/T5383014"
    },
    {
      "id": "T5147221",
      "title": "2 Bed - 160 Darling Zonnebloem",
      "neighborhood": "zonnebloem",
      "zone": "city_bowl",
      "price": 1950000,
      "size": 65,
      "bedrooms": 2,
      "bathrooms": 2,
      "parking": 2,
      "url": "https://www.privateproperty.co.za/for-sale/western-cape/cape-town/cape-town-city-bowl/zonnebloem/160-darling/T5147221"
    }
  ],
  "searchUrls": {
    "table_view": "https://www.privateproperty.co.za/for-sale/western-cape/cape-town/tableview-and-blouberg/table-view/444",
    "milnerton": "https://www.privateproperty.co.za/for-sale/western-cape/cape-town/milnerton/1399",
    "big_bay": "https://www.privateproperty.co.za/for-sale/western-cape/cape-town/tableview-and-blouberg/big-bay/764",
    "bloubergstrand": "https://www.privateproperty.co.za/for-sale/western-cape/cape-town/tableview-and-blouberg/bloubergstrand/441",
    "sea_point": "https://www.privateproperty.co.za/for-sale/western-cape/cape-town/atlantic-seaboard/sea-point/437",
    "green_point": "https://www.privateproperty.co.za/for-sale/western-cape/cape-town/atlantic-seaboard/green-point/864",
    "mouille_point": "https://www.privateproperty.co.za/for-sale/western-cape/cape-town/atlantic-seaboard/mouille-point/1596",
    "three_anchor_bay": "https://www.privateproperty.co.za/for-sale/western-cape/cape-town/atlantic-seaboard/three-anchor-bay/860",
    "de_waterkant": "https://www.privateproperty.co.za/for-sale/western-cape/cape-town/cape-town-city-bowl/de-waterkant/1503",
    "bo_kaap": "https://www.privateproperty.co.za/for-sale/western-cape/cape-town/cape-town-city-bowl/bo-kaap/2850",
    "cape_town_city_centre": "https://www.privateproperty.co.za/for-sale/western-cape/cape-town/cape-town-city-bowl/cape-town-city-centre/436",
    "gardens": "https://www.privateproperty.co.za/for-sale/western-cape/cape-town/cape-town-city-bowl/gardens/861",
    "tamboerskloof": "https://www.privateproperty.co.za/for-sale/western-cape/cape-town/cape-town-city-bowl/tamboerskloof/856",
    "vredehoek": "https://www.privateproperty.co.za/for-sale/western-cape/cape-town/cape-town-city-bowl/vredehoek/862",
    "woodstock": "https://www.privateproperty.co.za/for-sale/western-cape/cape-town/cape-town-city-bowl/woodstock/438",
    "observatory": "https://www.privateproperty.co.za/for-sale/western-cape/cape-town/cape-town-city-bowl/observatory/1098",
    "salt_river": "https://www.privateproperty.co.za/for-sale/western-cape/cape-town/cape-town-city-bowl/salt-river/1099",
    "claremont": "https://www.privateproperty.co.za/for-sale/western-cape/cape-town/southern-suburbs/claremont/433",
    "rondebosch": "https://www.privateproperty.co.za/for-sale/western-cape/cape-town/southern-suburbs/rondebosch/435",
    "zonnebloem": "https://www.privateproperty.co.za/for-sale/western-cape/cape-town/cape-town-city-bowl/zonnebloem/880"
  },
  "priceAnalysis": {
    "west_coast_affordable": {
      "minPrice": 975000,
      "maxPrice": 1500000,
      "avgSize": 44,
      "typicalYield": "5-6%",
      "note": "Table View et Milnerton = meilleurs prix de la zone kitesurf"
    },
    "west_coast_premium": {
      "minPrice": 2000000,
      "maxPrice": 7000000,
      "note": "Big Bay / Eden on the Bay = vue mer premium, rendement plus faible"
    },
    "eastern_emerging": {
      "minPrice": 1100000,
      "maxPrice": 2700000,
      "avgSize": 55,
      "typicalYield": "4-5%",
      "note": "Woodstock, Observatory, Salt River = gentrification, jeunes pros"
    },
    "atlantic_seaboard": {
      "minPrice": 2500000,
      "maxPrice": 3000000,
      "avgSize": 40,
      "typicalYield": "3-4%",
      "note": "Sea Point, Green Point = prix eleve mais forte demande Airbnb"
    },
    "city_bowl": {
      "minPrice": 1100000,
      "maxPrice": 2900000,
      "avgSize": 45,
      "typicalYield": "3.5-4.5%",
      "note": "City Centre, De Waterkant, Bo-Kaap = central, touristes"
    },
    "southern_suburbs": {
      "minPrice": 1400000,
      "maxPrice": 2900000,
      "avgSize": 55,
      "typicalYield": "4-5%",
      "note": "Claremont, Rondebosch = universites, familles, stable"
    }
  }
}
